README.md
setup.py
pirouz/__init__.py
pirouz/middleware.py
pirouz/response.py
pirouz/utils.py
pirouz/wsgi.py
pirouz.egg-info/PKG-INFO
pirouz.egg-info/SOURCES.txt
pirouz.egg-info/dependency_links.txt
pirouz.egg-info/requires.txt
pirouz.egg-info/top_level.txt
pirouz/orm/__init__.py
pirouz/orm/columns.py
pirouz/orm/db.py
pirouz/orm/operators.py
pirouz/test/__init__.py
pirouz/test/test_responses.py